[
  {
    "nonterminal": "RefBT",
    "forward": [
      [],
      [[0, "$INDEX - 1"]],
      [[0, "$INDEX - 1"]],
      [[0, "$INDEX - 1"], [1, "$INDEX - 1"]],
      [[0, "$INDEX"]]
    ],
    "backward": [
      "1",
      "$ASSIGN[0] + 1",
      "$ASSIGN[0] + 1",
      "($ASSIGN[0] + 1) U ($ASSIGN[1] + 1)",
      "$ASSIGN[0]"
    ]
  },
  {
    "nonterminal": "RefTP",
    "forward": [
      [],
      [],
      [[0, "$INDEX - 1"]],
      [[0, "$INDEX - 1"]],
      [[0, "$INDEX - 1"]],
      [[0, "$INDEX - 1"]],
      [[0, "$INDEX - 1"], [1, "$INDEX - 1"]],
      [[0, "$INDEX - 1"], [1, "$INDEX - 1"]],
      [[0, "$INDEX"], [1, "$INDEX - 1"]]
    ],
    "backward": [
      "1",
      "1",
      "$ASSIGN[0] + 1",
      "$ASSIGN[0] + 1",
      "$ASSIGN[0] + 1",
      "$ASSIGN[0] + 1",
      "($ASSIGN[0] + 1) U ($ASSIGN[1] + 1)",
      "($ASSIGN[0] + 1) U ($ASSIGN[1] + 1)",
      "$ASSIGN[0] U ($ASSIGN[1] + 1)"
    ]
  }
]